.coveragerc
.gitignore
.readthedocs.yml
AUTHORS.rst
CHANGELOG.rst
CONTRIBUTING.rst
LICENSE.txt
README.rst
pyproject.toml
setup.cfg
setup.py
tox.ini
docs/Makefile
docs/authors.rst
docs/changelog.rst
docs/conf.py
docs/contributing.rst
docs/index.rst
docs/license.rst
docs/readme.rst
docs/requirements.txt
docs/_static/.gitignore
src/snpediator/__init__.py
src/snpediator/local_db.py
src/snpediator/query_rsid.py
src/snpediator/skeleton.py
src/snpediator/snpediator_main.py
src/snpediator.egg-info/PKG-INFO
src/snpediator.egg-info/SOURCES.txt
src/snpediator.egg-info/dependency_links.txt
src/snpediator.egg-info/entry_points.txt
src/snpediator.egg-info/not-zip-safe
src/snpediator.egg-info/requires.txt
src/snpediator.egg-info/top_level.txt
tests/conftest.py
tests/test_skeleton.py