Metadata-Version: 2.1
Name: snpediator
Version: 0.0.0
Summary: Add a short description here!
Home-page: https://github.com/pyscaffold/pyscaffold/
Author: dcarrillox
Author-email: dcarrillo.bioinf@gmail.com
License: MIT
Project-URL: Documentation, https://pyscaffold.org/
Platform: any
Classifier: Development Status :: 4 - Beta
Classifier: Programming Language :: Python
Provides-Extra: testing
License-File: LICENSE.txt
